pagecraft/__init__.py
pagecraft/alchemy.py
pagecraft/base.py
pagecraft/page.py
pagecraft/pagecraft.py
pagecraft-0.0.6.dist-info/METADATA
pagecraft-0.0.6.dist-info/WHEEL
pagecraft-0.0.6.dist-info/licenses/LICENSE
pagecraft-0.0.6.dist-info/RECORD
