Metadata-Version: 2.1
Name: pagecraft
Version: 0.0.6
Summary: Powerful package and easy to use that simplifies the creation of pagination in your apps
Project-URL: Homepage, https://github.com/raulodev/pagecraft
Project-URL: Bug Tracker, https://github.com/raulodev/pagecraft/issues
Author-email: Raul Cobiellas <raulodev@gmail.com>
License-File: LICENSE
Classifier: License :: OSI Approved :: MIT License
Classifier: Operating System :: OS Independent
Classifier: Programming Language :: Python :: 3
Requires-Python: >=3.7
